wnstatmech/__about__.py
wnstatmech/__init__.py
wnstatmech/base.py
wnstatmech/boson.py
wnstatmech/fermion.py
wnstatmech-1.0.4.dist-info/licenses/LICENSE.txt
wnstatmech-1.0.4.dist-info/METADATA
wnstatmech-1.0.4.dist-info/WHEEL
wnstatmech-1.0.4.dist-info/top_level.txt
wnstatmech-1.0.4.dist-info/RECORD
