Metadata-Version: 2.4
Name: wnstatmech
Version: 1.0.4
Summary: Package for handling the statistical mechanics of fermions and bosons
Author-email: "Bradley S. Meyer" <mbradle@g.clemson.edu>, "Lucas S. Walls" <lwalls@g.clemson.edu>
Maintainer-email: "Bradley S. Meyer" <mbradle@g.clemson.edu>
License-Expression: GPL-3.0-or-later
Project-URL: Documentation, https://wnstatmech.readthedocs.org
Project-URL: Repository, https://github.com/mbradle/wnstatmech.git
Project-URL: Bug Tracker, https://github.com/mbradle/wnstatmech/issues
Keywords: astronomy, nuclear astrophysics
Classifier: Development Status :: 5 - Production/Stable
Classifier: Intended Audience :: Science/Research
Classifier: Topic :: Scientific/Engineering :: Astronomy
Classifier: Programming Language :: Python :: 3
Requires-Python: >=3.10
License-File: LICENSE.txt
Requires-Dist: scipy
Requires-Dist: numpy
Requires-Dist: gslconsts
Dynamic: license-file
